magmalink/Connection.py
magmalink/Filters.py
magmalink/Magma.py
magmalink/Node.py
magmalink/Player.py
magmalink/Plugins.py
magmalink/Queue.py
magmalink/Rest.py
magmalink/SearchPlatforms.py
magmalink/Track.py
magmalink/__init__.py
magmalink/autoplay.py
magmalink/fetchImage.py
magmalink/index.py
magmalink/main.py
magmalink-1.3.0.dist-info/licenses/LICENSE
magmalink-1.3.0.dist-info/METADATA
magmalink-1.3.0.dist-info/WHEEL
magmalink-1.3.0.dist-info/top_level.txt
magmalink-1.3.0.dist-info/RECORD
