Metadata-Version: 2.4
Name: MagmaLink
Version: 1.3.0
Summary: A simple lavalink wrapper easy to use
Home-page: https://github.com/southctrl/magmalink
Author: southctrl
Author-email: rive4785@gmail.com
Classifier: Programming Language :: Python :: 3
Classifier: License :: OSI Approved :: MIT License
Classifier: Operating System :: OS Independent
License-File: LICENSE
Dynamic: author
Dynamic: author-email
Dynamic: classifier
Dynamic: description
Dynamic: description-content-type
Dynamic: home-page
Dynamic: license-file
Dynamic: summary
